islabtech_upw_sensor_v1/__init__.py
islabtech_upw_sensor_v1/system_status.py
islabtech_upw_sensor_v1/_devices/__init__.py
islabtech_upw_sensor_v1/_devices/_implementations/__init__.py
islabtech_upw_sensor_v1/_devices/_implementations/interface.py
islabtech_upw_sensor_v1/_devices/_implementations/network.py
islabtech_upw_sensor_v1/examples/0100 getting started.ipynb
islabtech_upw_sensor_v1/examples/0100 getting started.py
islabtech_upw_sensor_v1/examples/0200 fetch metadata.ipynb
islabtech_upw_sensor_v1/examples/0200 fetch metadata.py
islabtech_upw_sensor_v1/measurements/__init__.py
islabtech_upw_sensor_v1-0.1.5.dist-info/METADATA
islabtech_upw_sensor_v1-0.1.5.dist-info/WHEEL
islabtech_upw_sensor_v1-0.1.5.dist-info/licenses/LICENSE.txt
islabtech_upw_sensor_v1-0.1.5.dist-info/licenses/NOTICE.txt
islabtech_upw_sensor_v1-0.1.5.dist-info/RECORD
