Metadata-Version: 2.3
Name: islabtech_upw_sensor_v1
Version: 0.1.5
Summary: Python client for the ISLabTech UPW sensor
Project-URL: Bug Tracker, https://gitlab.com/islabtech/upw-sensor/remote-python
Author-email: Ilka Schulz <ilka@islabtech.com>
License-File: LICENSE.txt
License-File: NOTICE.txt
Classifier: Natural Language :: English
Classifier: Operating System :: OS Independent
Classifier: Programming Language :: Python :: 3.7
Requires-Python: >=3.7
Requires-Dist: requests
